Shimano_PyTools/ExcelOpera.py
Shimano_PyTools/MSSqlDBUtils.py
Shimano_PyTools/PopUp.py
Shimano_PyTools/__init__.py
Shimano_PyTools-0.0.5.dist-info/LICENSE
Shimano_PyTools-0.0.5.dist-info/METADATA
Shimano_PyTools-0.0.5.dist-info/WHEEL
Shimano_PyTools-0.0.5.dist-info/top_level.txt
Shimano_PyTools-0.0.5.dist-info/RECORD
